{"info":{"subdir":"linux-64"},"packages":{"lightningsim_trace-0.2.2.1-py310h3fd9d12_1.tar.bz2":{"build":"py310h3fd9d12_1","build_number":1,"depends":["binutils","gcc_linux-64","gxx_linux-64","jinja2","libedit >=3.1.20191231,<3.2.0a0","libgcc >=14","libstdcxx >=14","libxml2 >=2.12.7,<3.0a0","libzlib >=1.3.1,<2.0a0","llvmlite","ncurses >=6.5,<7.0a0","pyelftools","python >=3.10,<3.11.0a0","python-socketio","python_abi 3.10.* *_cp310","sysroot_linux-64 2.17.*","uvicorn-standard","zstd >=1.5.6,<1.6.0a0"],"license":"AGPL-3.0-only","md5":"4cab6ea83171cbf5e7369d4962c819db","name":"lightningsim_trace","sha256":"be6d431511d4fd1c2dadbf64dcd9139c4e88ab15e1593fd3ab698381437523f5","size":56808169,"subdir":"linux-64","timestamp":1725487300727,"version":"0.2.2.1"},"lightningsim_trace-0.2.2.1-py311h3fd9d12_1.tar.bz2":{"build":"py311h3fd9d12_1","build_number":1,"depends":["binutils","gcc_linux-64","gxx_linux-64","jinja2","libedit >=3.1.20191231,<3.2.0a0","libgcc >=14","libstdcxx >=14","libxml2 >=2.12.7,<3.0a0","libzlib >=1.3.1,<2.0a0","llvmlite","ncurses >=6.5,<7.0a0","pyelftools","python >=3.11,<3.12.0a0","python-socketio","python_abi 3.11.* *_cp311","sysroot_linux-64 2.17.*","uvicorn-standard","zstd >=1.5.6,<1.6.0a0"],"license":"AGPL-3.0-only","md5":"320fb787303d314ab4a65608f10b92e8","name":"lightningsim_trace","sha256":"c7a816cb66081f0ffcc710d35ed6e9cc2de855b284887bcd167262aca0f65608","size":56909033,"subdir":"linux-64","timestamp":1725487450621,"version":"0.2.2.1"},"lightningsim_trace-0.2.2.1-py312h3fd9d12_1.tar.bz2":{"build":"py312h3fd9d12_1","build_number":1,"depends":["binutils","gcc_linux-64","gxx_linux-64","jinja2","libedit >=3.1.20191231,<3.2.0a0","libgcc >=14","libstdcxx >=14","libxml2 >=2.12.7,<3.0a0","libzlib >=1.3.1,<2.0a0","llvmlite","ncurses >=6.5,<7.0a0","pyelftools","python >=3.12,<3.13.0a0","python-socketio","python_abi 3.12.* *_cp312","sysroot_linux-64 2.17.*","uvicorn-standard","zstd >=1.5.6,<1.6.0a0"],"license":"AGPL-3.0-only","md5":"51563d8787cbb430ad1847e683a59713","name":"lightningsim_trace","sha256":"ca3b9879a1a540c51dba01fa69929e29fef506e571d821b11670748e5661efdb","size":56905405,"subdir":"linux-64","timestamp":1725487594210,"version":"0.2.2.1"}},"packages.conda":{},"removed":[],"repodata_version":1}